pytarjimon.py
pytarjimon-0.0.1.dist-info/WHEEL
pytarjimon-0.0.1.dist-info/METADATA
pytarjimon-0.0.1.dist-info/RECORD
